vennproteomics/__init__.py
vennproteomics/analysis.py
vennproteomics-0.1.0.dist-info/WHEEL
vennproteomics-0.1.0.dist-info/METADATA
vennproteomics-0.1.0.dist-info/RECORD
